LICENSE
MANIFEST.in
README.md
README.rst
RELEASE-VERSION
setup.py
version.py
dossier/__init__.py
dossier.web.egg-info/PKG-INFO
dossier.web.egg-info/SOURCES.txt
dossier.web.egg-info/dependency_links.txt
dossier.web.egg-info/entry_points.txt
dossier.web.egg-info/namespace_packages.txt
dossier.web.egg-info/not-zip-safe
dossier.web.egg-info/requires.txt
dossier.web.egg-info/top_level.txt
dossier/extraction/__init__.py
dossier/extraction/usernames.py
dossier/extraction/tests/__init__.py
dossier/extraction/tests/test_usernames.py
dossier/web/__init__.py
dossier/web/builder.py
dossier/web/config.py
dossier/web/filters.py
dossier/web/folder.py
dossier/web/interface.py
dossier/web/label_folders.py
dossier/web/routes.py
dossier/web/run.py
dossier/web/search_engines.py
dossier/web/util.py
dossier/web/wsgi.py
dossier/web/static/v1/deps/Dossier.js
dossier/web/static/v1/deps/SortingQueue.css
dossier/web/static/v1/deps/SortingQueue.js
dossier/web/tests/__init__.py
dossier/web/tests/test_config.py
dossier/web/tests/test_filter_preds.py
dossier/web/tests/test_folder.py
dossier/web/tests/test_label_folders.py
dossier/web/tests/test_routes.py
dossier/web/tests/test_search_engines.py