Metadata-Version: 1.1
Name: dossier.web
Version: 0.7.13
Summary: DossierStack web services
Home-page: http://github.com/dossier/dossier.web
Author: Diffeo, Inc.
Author-email: support@diffeo.com
License: MIT
Platform: UNKNOWN
Classifier: Development Status :: 3 - Alpha
Classifier: Topic :: Utilities
Classifier: License :: OSI Approved :: MIT License
